vhsd_rust.cpython-310-x86_64-linux-gnu.so
cvbsdecode/__init__.py
cvbsdecode/main.py
cvbsdecode/process.py
lddecode/__init__.py
lddecode/commpy_filters.py
lddecode/core.py
lddecode/efm_pll.py
lddecode/fdls.py
lddecode/fft8.py
lddecode/main.py
lddecode/utils.py
lddecode/utils_logging.py
lddecode/utils_plotting.py
lddecode/version
vhs_decode-0.3.8.1.data/scripts/cx-expander
vhs_decode-0.3.8.1.data/scripts/decode.py
vhs_decode-0.3.8.1.data/scripts/ld-cut
vhs_decode.libs/libgcc_s-0cd532bd.so.1
vhsdecode/__init__.py
vhsdecode/_version.py
vhsdecode/chroma.py
vhsdecode/cmdcommons.py
vhsdecode/compute_video_filters.py
vhsdecode/debug_plot.py
vhsdecode/demod.py
vhsdecode/demodcache.py
vhsdecode/doc.py
vhsdecode/field.py
vhsdecode/field_averages.py
vhsdecode/filter_plot.py
vhsdecode/formats.py
vhsdecode/hilbert.c
vhsdecode/hilbert.cpython-310-x86_64-linux-gnu.so
vhsdecode/hilbert.pyx
vhsdecode/leveldetect.py
vhsdecode/linear_filter.c
vhsdecode/linear_filter.cpython-310-x86_64-linux-gnu.so
vhsdecode/linear_filter.pyx
vhsdecode/linelocs.py
vhsdecode/load_params_json.py
vhsdecode/main.py
vhsdecode/nonlinear_filter.py
vhsdecode/process.py
vhsdecode/rust_utils.py
vhsdecode/sync.c
vhsdecode/sync.cpython-310-x86_64-linux-gnu.so
vhsdecode/sync.pyx
vhsdecode/utils.py
vhsdecode/video_eq.py
vhsdecode/addons/FMdeemph.py
vhsdecode/addons/__init__.py
vhsdecode/addons/biquad.py
vhsdecode/addons/chromaAFC.py
vhsdecode/addons/chromasep.py
vhsdecode/addons/gnuradioZMQ.py
vhsdecode/addons/resync.py
vhsdecode/addons/vsyncserration.py
vhsdecode/format_defs/__init__.py
vhsdecode/format_defs/betamax.py
vhsdecode/format_defs/cvbs.py
vhsdecode/format_defs/eiaj.py
vhsdecode/format_defs/svhs-sp-linear-subdeemphasis-17734475.txt
vhsdecode/format_defs/svhs-sp-linear-subdeemphasis-40000000.txt
vhsdecode/format_defs/typec.py
vhsdecode/format_defs/umatic.py
vhsdecode/format_defs/vcr.py
vhsdecode/format_defs/vhs.py
vhs_decode-0.3.8.1.dist-info/METADATA
vhs_decode-0.3.8.1.dist-info/WHEEL
vhs_decode-0.3.8.1.dist-info/entry_points.txt
vhs_decode-0.3.8.1.dist-info/top_level.txt
vhs_decode-0.3.8.1.dist-info/RECORD
vhs_decode-0.3.8.1.dist-info/licenses/LICENSE
