Metadata-Version: 2.4
Name: vhs_decode
Version: 0.3.8.1
Summary: Software Decoder for raw rf captures of laserdisc, vhs and other analog video formats
License:                     GNU GENERAL PUBLIC LICENSE
Project-URL: Homepage, https://www.domesday86.com
Keywords: laserdisc,vhs,video,tape,decoder
Classifier: Topic :: Multimedia :: Video
Classifier: Programming Language :: Rust
Requires: matplotlib
Requires: numba
Requires: numpy
Requires: scipy
Requires: Cython
Provides: lddecode
Requires-Python: >=3.8
License-File: LICENSE
Requires-Dist: numpy>=1.22
Requires-Dist: numba>=0.58.1
Requires-Dist: scipy>=1.10.1
Requires-Dist: soxr
Requires-Dist: static-ffmpeg
Requires-Dist: cython
Requires-Dist: soundfile>=0.13.1
Requires-Dist: sounddevice
Requires-Dist: importlib_resources>=5.0; python_version < "3.10"
Requires-Dist: matplotlib
Requires-Dist: noisereduce>=2.0.0
Requires-Dist: setproctitle
Provides-Extra: intel
Requires-Dist: intel-cmplr-lib-rt; extra == "intel"
Requires-Dist: icc_rt; extra == "intel"
Provides-Extra: hifi-gui
Requires-Dist: PyQt5>=5.14.1; extra == "hifi-gui"
Provides-Extra: hifi-gui-qt6
Requires-Dist: PyQt6>=6.4.2; extra == "hifi-gui-qt6"
Provides-Extra: hifi-gnuradio
Requires-Dist: pyzmq; extra == "hifi-gnuradio"
Provides-Extra: gnuradio
Requires-Dist: pyzmq; extra == "gnuradio"
Dynamic: license-file
Dynamic: provides
Dynamic: requires
